VizDat/__init__.py
VizDat/main.py
VizDat-1.0.3.dist-info/METADATA
VizDat-1.0.3.dist-info/WHEEL
VizDat-1.0.3.dist-info/top_level.txt
VizDat-1.0.3.dist-info/RECORD
