Metadata-Version: 2.1
Name: VizDat
Version: 1.0.3
Summary: A fast and simple data visualization library for tabular data.
Home-page: https://github.com/MustafaFarajAllah/VizDat
Author: Mustafa FarajAllah
Author-email: mustafa.farajallah99@gmail.com
Classifier: Programming Language :: Python :: 3
Classifier: License :: OSI Approved :: MIT License
Classifier: Operating System :: OS Independent
Requires-Python: >=3.6
Requires-Dist: matplotlib
Requires-Dist: pandas
Requires-Dist: numpy
Requires-Dist: scipy
